carbontracking/__init__.py
carbontracking/carbontracking.py
carbontracking/cpu.py
carbontracking/db_app.py
carbontracking/gpu.py
carbontracking/hardware.py
carbontracking/input.py
carbontracking/logger.py
carbontracking/powermetrics.py
carbontracking/rapl.py
carbontracking/tracker.py
carbontracking/units.py
carbontracking/util.py
carbontracking/codecarbon/__init__.py
carbontracking/codecarbon/_version.py
carbontracking/codecarbon/emissions_tracker.py
carbontracking/codecarbon/input.py
carbontracking/codecarbon/output.py
carbontracking/codecarbon/cli/__init__.py
carbontracking/codecarbon/cli/cli_utils.py
carbontracking/codecarbon/cli/main.py
carbontracking/codecarbon/core/__init__.py
carbontracking/codecarbon/core/api_client.py
carbontracking/codecarbon/core/cloud.py
carbontracking/codecarbon/core/co2_signal.py
carbontracking/codecarbon/core/config.py
carbontracking/codecarbon/core/cpu.py
carbontracking/codecarbon/core/emissions.py
carbontracking/codecarbon/core/gpu.py
carbontracking/codecarbon/core/measure.py
carbontracking/codecarbon/core/powermetrics.py
carbontracking/codecarbon/core/rapl.py
carbontracking/codecarbon/core/schemas.py
carbontracking/codecarbon/core/units.py
carbontracking/codecarbon/core/util.py
carbontracking/codecarbon/external/__init__.py
carbontracking/codecarbon/external/geography.py
carbontracking/codecarbon/external/hardware.py
carbontracking/codecarbon/external/logger.py
carbontracking/codecarbon/external/scheduler.py
carbontracking/codecarbon/external/task.py
carbontracking/codecarbon/prometheus/__init__.py
carbontracking/codecarbon/prometheus/metric_definitions.py
carbontracking/codecarbon/prometheus/prometheus.py
carbontracking/codecarbon/viz/__init__.py
carbontracking/codecarbon/viz/carbonboard.py
carbontracking/codecarbon/viz/carbonboard_on_api.py
carbontracking/codecarbon/viz/components.py
carbontracking/codecarbon/viz/data.py
carbontracking/codecarbon/viz/assets/__init__.py
carbontracking/static/assets/bootstrap/css/bootstrap.min.css
carbontracking-0.0.50.dist-info/METADATA
carbontracking-0.0.50.dist-info/WHEEL
carbontracking-0.0.50.dist-info/top_level.txt
carbontracking-0.0.50.dist-info/RECORD
