Metadata-Version: 2.2
Name: carbontracking
Version: 0.0.50
Summary: A carbon tracking library for Python applications
Home-page: 
Author: Peter Rolfes
Author-email: pero01@dfki.de
License: MIT
Classifier: License :: OSI Approved :: MIT License
Classifier: Programming Language :: Python :: 3.10
Classifier: Operating System :: OS Independent
Requires-Python: >=3.10
Requires-Dist: codecarbon
Requires-Dist: requests
Requires-Dist: numpy
Requires-Dist: pandas
Requires-Dist: psutil
Requires-Dist: rapidfuzz
Requires-Dist: flask
Requires-Dist: flask_sqlalchemy
Requires-Dist: sqlalchemy
Requires-Dist: statistics
Requires-Dist: collection
Requires-Dist: thread
Requires-Dist: jsons
Requires-Dist: codecarbon
Requires-Dist: entsoe-py
Provides-Extra: dev
Requires-Dist: pytest>=7.0; extra == "dev"
Requires-Dist: twine>=4.0.2; extra == "dev"
Dynamic: author
Dynamic: author-email
Dynamic: classifier
Dynamic: description
Dynamic: description-content-type
Dynamic: license
Dynamic: provides-extra
Dynamic: requires-dist
Dynamic: requires-python
Dynamic: summary
